counter-1-12/counter.v
module counter(
    input clk,
    input enable,
    input reset,
    input load,
    input [3:0] d,
    output reg [3:0] q
);
    initial q = 4'b0001;
    always @(posedge clk) begin
        //$display("%d", q);
        /*
        casex({enable, reset, load})
            3'b0xx: ; //nothing
            3'b11x: q <= 4'b0001;
            3'b101: q <= d;
            3'b100: if (q < 12) q <= q + 4'b0001; else q <= 4'b0001;
        endcase
        */
        if (enable == 1) begin
            if (reset == 1) begin
                q <= 4'b0001;
            end
            else begin
                if (load == 1) q <= d;
                else if (q < 12) q <= q + 1;
                else q <= 4'b0001;
            end
        end
    end
endmodule

counter-1-12/tb_counter.v
module tb;
    initial begin
    	$dumpfile("test.vcd");
    	$dumpvars(0,tb);
	end

    reg clk, load, reset;
    reg [3:0] d;
    reg [31:0] cnt;
    wire [3:0] q;

    always #5 clk <= ~clk;
    always @(posedge clk) begin
        $display("%d| %d| %d", $time, q, cnt);
        cnt <= cnt + 1;
        
        if (cnt == 10) load <= 1'b1;
        else load <= 1'b0;
    end

    counter c(clk, 1'b1, reset, load, d, q);

    initial begin
        cnt <= 0;
        reset <= 1'b0;
        clk <= 1'b0;
        load <= 1'b0;
        d <= 4'b1001;

        #500 $finish;
    end
endmodule

counter-1-12/test.vcd
$date
	Tue Jul  6 20:09:56 2021
$end
$version
	Icarus Verilog
$end
$timescale
	1s
$end
$scope module tb $end
$var wire 4 ! q [3:0] $end
$var reg 1 " clk $end
$var reg 32 # cnt [31:0] $end
$var reg 4 $ d [3:0] $end
$var reg 1 % load $end
$var reg 1 & reset $end
$scope module c $end
$var wire 1 " clk $end
$var wire 4 ' d [3:0] $end
$var wire 1 ( enable $end
$var wire 1 % load $end
$var wire 1 & reset $end
$var reg 4 ) q [3:0] $end
$upscope $end
$upscope $end
$enddefinitions $end
#0
$dumpvars
b1 )
1(
b1001 '
0&
0%
b1001 $
b0 #
0"
b1 !
$end
#5
b10 !
b10 )
b1 #
1"
#10
0"
#15
b10 #
b11 !
b11 )
1"
#20
0"
#25
b100 !
b100 )
b11 #
1"
#30
0"
#35
b100 #
b101 !
b101 )
1"
#40
0"
#45
b110 !
b110 )
b101 #
1"
#50
0"
#55
1&
b110 #
b111 !
b111 )
1"
#60
0"
#65
b1 !
b1 )
0&
b111 #
1"
#70
0"
#75
b1000 #
b10 !
b10 )
1"
#80
0"
#85
b11 !
b11 )
b1001 #
1"
#90
0"
#95
b1010 #
b100 !
b100 )
1"
#100
0"
#105
b101 !
b101 )
b1011 #
1"
#110
0"
#115
b1100 #
b110 !
b110 )
1"
#120
0"
#125
b111 !
b111 )
b1101 #
1"
#130
0"
#135
b1110 #
b1000 !
b1000 )
1"
#140
0"
#145
b1001 !
b1001 )
b1111 #
1"
#150
0"
#155
b10000 #
b1010 !
b1010 )
1"
#160
0"
#165
b1011 !
b1011 )
b10001 #
1"
#170
0"
#175
b10010 #
b1100 !
b1100 )
1"
#180
0"
#185
b1 !
b1 )
b10011 #
1"
#190
0"
#195
b10100 #
b10 !
b10 )
1"
#200
0"
#205
b11 !
b11 )
b10101 #
1"
#210
0"
#215
b10110 #
b100 !
b100 )
1"
#220
0"
#225
b101 !
b101 )
b10111 #
1"
#230
0"
#235
b11000 #
b110 !
b110 )
1"
#240
0"
#245
b111 !
b111 )
b11001 #
1"
#250
0"
#255
b11010 #
b1000 !
b1000 )
1"
#260
0"
#265
b1001 !
b1001 )
b11011 #
1"
#270
0"
#275
b11100 #
b1010 !
b1010 )
1"
#280
0"
#285
b1011 !
b1011 )
b11101 #
1"
#290
0"
#295
b11110 #
b1100 !
b1100 )
1"
#300
0"
#305
b1 !
b1 )
b11111 #
1"
#310
0"
#315
b100000 #
b10 !
b10 )
1"
#320
0"
#325
b11 !
b11 )
b100001 #
1"
#330
0"
#335
b100010 #
b100 !
b100 )
1"
#340
0"
#345
b101 !
b101 )
b100011 #
1"
#350
0"
#355
b100100 #
b110 !
b110 )
1"
#360
0"
#365
b111 !
b111 )
b100101 #
1"
#370
0"
#375
b100110 #
b1000 !
b1000 )
1"
#380
0"
#385
b1001 !
b1001 )
b100111 #
1"
#390
0"
#395
b101000 #
b1010 !
b1010 )
1"
#400
0"
#405
b1011 !
b1011 )
b101001 #
1"
#410
0"
#415
b101010 #
b1100 !
b1100 )
1"
#420
0"
#425
b1 !
b1 )
b101011 #
1"
#430
0"
#435
b101100 #
b10 !
b10 )
1"
#440
0"
#445
b11 !
b11 )
b101101 #
1"
#450
0"
#455
b101110 #
b100 !
b100 )
1"
#460
0"
#465
b101 !
b101 )
b101111 #
1"
#470
0"
#475
b110000 #
b110 !
b110 )
1"
#480
0"
#485
b111 !
b111 )
b110001 #
1"
#490
0"
#495
b110010 #
b1000 !
b1000 )
1"
